pytedjmi/__init__.py
pytedjmi/core.py
pytedjmi/urls.py
pytedjmi-0.4.3.dist-info/entry_points.txt
pytedjmi-0.4.3.dist-info/LICENSE.md
pytedjmi-0.4.3.dist-info/WHEEL
pytedjmi-0.4.3.dist-info/METADATA
pytedjmi-0.4.3.dist-info/RECORD
